{
  "visualID": 2225924,
  "title": "Binary Epoch Time",
  "description": "Unix epoch time (seconds since Jan 1, 1970) in binary on a 6x6 grid with white for 1s and black for 0s. The grey squares show the limitation of 32-bit computer systems that will fail to represent time accurately after January 19, 2038.",
  "instructions": "",
  "tags": [],
  "license": "by-sa",
  "isDraft": 0,
  "createdOn": "2024-03-31 21:46:31",
  "updatedOn": "2025-12-30 08:03:21",
  "filesUpdatedOn": null,
  "thumbnailUpdatedOn": "2024-03-31 21:46:31",
  "videoUpdatedOn": null,
  "parentID": null,
  "engineID": 2257,
  "isTutorial": 0,
  "isTemplate": 0,
  "hasTimeline": 0,
  "libraries": [],
  "templateID": null,
  "userID": 4474,
  "engineURL": "https://cdn.jsdelivr.net/npm/p5@1.9.2/lib/p5.js",
  "mode": "p5js",
  "width": 200,
  "height": 200
}
